ics2ews/sync.py
ics2ews/version.py
ics2ews-0.1.dist-info/LICENSE.txt
ics2ews-0.1.dist-info/METADATA
ics2ews-0.1.dist-info/WHEEL
ics2ews-0.1.dist-info/entry_points.txt
ics2ews-0.1.dist-info/top_level.txt
ics2ews-0.1.dist-info/RECORD
